visual_automata/__init__.py
visual_automata/colors.py
visual_automata/fa/dfa.py
visual_automata/fa/nfa.py
visual_automata-1.1.1.dist-info/LICENSE.txt
visual_automata-1.1.1.dist-info/METADATA
visual_automata-1.1.1.dist-info/WHEEL
visual_automata-1.1.1.dist-info/top_level.txt
visual_automata-1.1.1.dist-info/RECORD
